res_wind_up-0.4.4.dist-info/licenses/LICENSE.txt
wind_up/__init__.py
wind_up/backporting.py
wind_up/caching.py
wind_up/circular_math.py
wind_up/combine_results.py
wind_up/constants.py
wind_up/conversions.py
wind_up/detrend.py
wind_up/interface.py
wind_up/long_term.py
wind_up/main_analysis.py
wind_up/models.py
wind_up/northing.py
wind_up/northing_utils.py
wind_up/optimize_northing.py
wind_up/pp_analysis.py
wind_up/reanalysis_data.py
wind_up/result_manager.py
wind_up/scada_funcs.py
wind_up/scada_power_curve.py
wind_up/smart_data.py
wind_up/waking_state.py
wind_up/wind_funcs.py
wind_up/windspeed_drift.py
wind_up/ws_est.py
wind_up/yaml_loader.py
wind_up/plots/__init__.py
wind_up/plots/combine_results_plots.py
wind_up/plots/data_coverage_plots.py
wind_up/plots/detrend_plots.py
wind_up/plots/input_data.py
wind_up/plots/long_term_plots.py
wind_up/plots/misc_plots.py
wind_up/plots/northing_plots.py
wind_up/plots/optimize_northing_plots.py
wind_up/plots/pp_analysis_plots.py
wind_up/plots/reanalysis_plots.py
wind_up/plots/scada_funcs_plots.py
wind_up/plots/scada_power_curve_plots.py
wind_up/plots/waking_state_plots.py
wind_up/plots/windspeed_drift_plots.py
wind_up/plots/ws_est_plots.py
wind_up/plots/yaw_direction_plots.py
res_wind_up-0.4.4.dist-info/METADATA
res_wind_up-0.4.4.dist-info/WHEEL
res_wind_up-0.4.4.dist-info/top_level.txt
res_wind_up-0.4.4.dist-info/RECORD
