Metadata-Version: 2.4
Name: res-wind-up
Version: 0.4.4
Summary: A tool to assess yield uplift of wind turbines
Author-email: Alex Clerc <alex.clerc@res-group.com>
License: BSD 3-Clause License
Project-URL: Homepage, https://github.com/resgroup/wind-up
Classifier: Development Status :: 4 - Beta
Classifier: Programming Language :: Python
Classifier: Programming Language :: Python :: 3.9
Classifier: Programming Language :: Python :: 3.10
Classifier: Programming Language :: Python :: 3.11
Classifier: Programming Language :: Python :: 3.12
Classifier: Programming Language :: Python :: 3.13
Classifier: Programming Language :: Python :: 3 :: Only
Classifier: License :: OSI Approved :: BSD License
Classifier: Operating System :: OS Independent
Classifier: Topic :: Scientific/Engineering
Requires-Python: <4.0,>=3.9
License-File: LICENSE.txt
Requires-Dist: eval-type-backport
Requires-Dist: geographiclib
Requires-Dist: matplotlib
Requires-Dist: pandas>=2.0.0
Requires-Dist: pyarrow
Requires-Dist: pydantic>=2.0.0
Requires-Dist: python-dotenv
Requires-Dist: pyyaml
Requires-Dist: ruptures
Requires-Dist: scipy
Requires-Dist: seaborn
Requires-Dist: tabulate
Requires-Dist: toml
Requires-Dist: tqdm
Requires-Dist: utm
Provides-Extra: dev
Requires-Dist: pytest; extra == "dev"
Requires-Dist: coverage; extra == "dev"
Requires-Dist: poethepoet; extra == "dev"
Requires-Dist: types-pyyaml; extra == "dev"
Requires-Dist: types-tabulate; extra == "dev"
Requires-Dist: types-toml; extra == "dev"
Requires-Dist: types-tqdm; extra == "dev"
Requires-Dist: types-requests; extra == "dev"
Requires-Dist: ruff; extra == "dev"
Requires-Dist: mypy; extra == "dev"
Requires-Dist: requests; extra == "dev"
Requires-Dist: pytest-env; extra == "dev"
Provides-Extra: examples
Requires-Dist: jupyterlab; extra == "examples"
Requires-Dist: notebook; extra == "examples"
Requires-Dist: ipywidgets; extra == "examples"
Requires-Dist: requests; extra == "examples"
Requires-Dist: ephem; extra == "examples"
Requires-Dist: flaml[automl]; extra == "examples"
Dynamic: license-file
